tokyo/__init__.py
tokyo/properties.py
tokyo/endpoints/anime.py
tokyo/endpoints/buffer.py
tokyo/endpoints/json.py
tokyo.py-0.0.4.dist-info/LICENSE
tokyo.py-0.0.4.dist-info/METADATA
tokyo.py-0.0.4.dist-info/WHEEL
tokyo.py-0.0.4.dist-info/top_level.txt
tokyo.py-0.0.4.dist-info/RECORD
