Metadata-Version: 2.1
Name: tokyo.py
Version: 0.0.4
Summary: Python library for interacting with Tokyo API (https://api.miduwu.ga/)
Home-page: https://github.com/Loxitoh/tokyo.py
Author: Loxitoh
Author-email: Loxitoh <loxitoh@gmail.com>
License: MIT License        
Project-URL: Homepage, https://github.com/Loxitoh/tokyo.py
Project-URL: Bug Tracker, https://github.com/Loxitoh/tokyo.py/issues
Classifier: Programming Language :: Python :: 3
Classifier: License :: OSI Approved :: MIT License
Classifier: Operating System :: OS Independent
Requires-Python: >=3.8
License-File: LICENSE
Requires-Dist: aiohttp
